stiq/__init__.py
stiq/config.py
stiq/loader.py
stiq-0.0.1.6.dist-info/LICENSE
stiq-0.0.1.6.dist-info/METADATA
stiq-0.0.1.6.dist-info/WHEEL
stiq-0.0.1.6.dist-info/top_level.txt
stiq-0.0.1.6.dist-info/RECORD
