Metadata-Version: 2.1
Name: stiq
Version: 0.0.1.6
Summary: Just an experiment for fun
Author: Thinh Vu
Author-email: mrthinh@live.com
Classifier: Programming Language :: Python :: 3
Classifier: License :: OSI Approved :: MIT License
Classifier: Operating System :: OS Independent
Requires-Python: >=3.7
License-File: LICENSE
Requires-Dist: vnstock
